forbesqotd/__init__.py
forbesqotd/qotd.py
forbesqotd-2.0.data/scripts/qotd
forbesqotd-2.0.dist-info/DESCRIPTION.rst
forbesqotd-2.0.dist-info/METADATA
forbesqotd-2.0.dist-info/RECORD
forbesqotd-2.0.dist-info/WHEEL
forbesqotd-2.0.dist-info/metadata.json
forbesqotd-2.0.dist-info/top_level.txt
